plone.uuid-2.0.2-py3.13-nspkg.pth
plone/uuid/__init__.py
plone/uuid/adapter.py
plone/uuid/browser.py
plone/uuid/configure.zcml
plone/uuid/generator.py
plone/uuid/handlers.py
plone/uuid/interfaces.py
plone/uuid/tests.py
plone_uuid-2.0.2.dist-info/METADATA
plone_uuid-2.0.2.dist-info/WHEEL
plone_uuid-2.0.2.dist-info/namespace_packages.txt
plone_uuid-2.0.2.dist-info/top_level.txt
plone_uuid-2.0.2.dist-info/RECORD
