Metadata-Version: 2.4
Name: plone.uuid
Version: 2.0.2
Summary: UUIDs for content items
Home-page: https://github.com/plone/plone.uuid
Author: Martin Aspeli
Author-email: optilude@gmail.com
License: BSD
Keywords: plone uuid
Classifier: Development Status :: 5 - Production/Stable
Classifier: Framework :: Plone
Classifier: Framework :: Plone :: 6.0
Classifier: Framework :: Plone :: Core
Classifier: Programming Language :: Python
Classifier: License :: OSI Approved :: BSD License
Classifier: Programming Language :: Python :: 3.8
Classifier: Programming Language :: Python :: 3.9
Classifier: Programming Language :: Python :: 3.10
Classifier: Programming Language :: Python :: 3.11
Requires-Python: >=3.8
Requires-Dist: Acquisition
Requires-Dist: setuptools
Requires-Dist: zope.component
Requires-Dist: zope.browserpage
Requires-Dist: zope.interface
Requires-Dist: zope.lifecycleevent
Requires-Dist: zope.publisher
Provides-Extra: test
Requires-Dist: zope.configuration; extra == "test"
Requires-Dist: zope.event; extra == "test"
Dynamic: author
Dynamic: author-email
Dynamic: classifier
Dynamic: description
Dynamic: description-content-type
Dynamic: home-page
Dynamic: keywords
Dynamic: license
Dynamic: provides-extra
Dynamic: requires-dist
Dynamic: requires-python
Dynamic: summary
